color_pallete.py
color_pallete-0.0.9.dist-info/METADATA
color_pallete-0.0.9.dist-info/WHEEL
color_pallete-0.0.9.dist-info/top_level.txt
color_pallete-0.0.9.dist-info/RECORD
